Metadata-Version: 1.0
Name: controlla
Version: 0.3
Summary: Gaussian distributions
Home-page: UNKNOWN
Author: Oguchi Ebuka Philip
Author-email: oguchiebuka919@gmail.com
License: UNKNOWN
Platform: UNKNOWN
